__init__.py
anacondas/__init__.py
anacondas/FileSystemModel/__init__.py
anacondas/FileSystemModel/_dir.py
anacondas/FileSystemModel/_file.py
anacondas/FileSystemModel/_path.py
anacondas-0.0.2.dist-info/LICENSE
anacondas-0.0.2.dist-info/METADATA
anacondas-0.0.2.dist-info/WHEEL
anacondas-0.0.2.dist-info/top_level.txt
anacondas-0.0.2.dist-info/RECORD
