Metadata-Version: 2.1
Name: anacondas
Version: 0.0.2
Summary: A tool library for Windows commands.
Author-email: 张恒华 <1652709417@qq.com>
Keywords: cmd,command,commands,Python,Python3,Python 3,Shell,Power Shell,PowerShell,Windows,Windows cmd,Windows command,Windows commands,Windows Shell,Windows Power Shell,Windows PowerShell
Classifier: Programming Language :: Python :: 3
Classifier: Programming Language :: Python :: 3.9
Classifier: Programming Language :: Python :: 3.10
Classifier: Programming Language :: Python :: 3.11
Classifier: Programming Language :: Python :: 3.12
Classifier: License :: OSI Approved :: MIT License
Classifier: Operating System :: Microsoft :: Windows
Requires-Python: >=3.9
License-File: LICENSE
Requires-Dist: pywin32
Requires-Dist: prettytable
